{
    "__parentReadjusting__": false,
    "_padding_": [
        0,
        0,
        0,
        0
    ],
    "_skin_": "se83aea32c3841aa893c3e9fb8df9ba2",
    "_srcKuid_": "d99c02a9711e4812a25c743584aa1ab7",
    "canUpdateUI": true,
    "channel": "mobile",
    "context": {},
    "dataDiffs": {
        "centerX": {
            "type": "string",
            "value": "50%"
        },
        "centerY": {
            "type": "string",
            "value": "50%"
        },
        "height": {
            "type": "string",
            "value": "90%"
        },
        "id": "Image0f64725833a0345",
        "imageScaleMode": 1,
        "src": "bestbuy.png",
        "width": {
            "type": "string",
            "value": "90%"
        },
        "zIndex": 1
    },
    "id": "Image0f64725833a0345",
    "instanceOf": "d99c02a9711e4812a25c743584aa1ab7",
    "isvisible": true,
    "kuid": "m45efd12b207462ea5a3c90d201d460f",
    "masterInstance": true,
    "name": "kony.ui.Image2",
    "parent": "FlexLogo",
    "pf": "HomeScreen",
    "topLevelInstanceKUID": "m72ea42d2b86412fbbe7fbf2d2a0101c",
    "wType": "Image"
}