{
    "AS_Form_3426423d2e274749b880a9b311dc8ad2": {
        "id": "AS_Form_3426423d2e274749b880a9b311dc8ad2",
        "type": "ACTION_SEQUENCE",
        "params": [{
            "datatype": "collection",
            "name": "eventobject"
        }],
        "contextObj": {
            "name": "HomeScreen",
            "type": "forms",
            "platform": null,
            "KUID": "490e7c9343aa4b7abe989ef881ac7a6c"
        },
        "language": "js",
        "actions": [{
            "id": "INVOKE_FUNCTION__ide_init_7d7b3f8da91a4cf5aa32edf9c6223f0e",
            "type": "INVOKE_FUNCTION",
            "sequenceKUID": "getCategeoryData",
            "display": "getCategeoryData",
            "inputparams": [],
            "callbackType": null,
            "disabled": null
        }, {
            "id": "INVOKE_FUNCTION__ide_init_56ff3f65df5c407c9c3cf35b8003306c",
            "type": "INVOKE_FUNCTION",
            "sequenceKUID": "homeInit",
            "display": "homeInit",
            "inputparams": [],
            "callbackType": null,
            "disabled": null
        }]
    }
}