{
    "AS_FlexContainer_23191767b5c94dcbaa7fe89acbe7a359": {
        "id": "AS_FlexContainer_23191767b5c94dcbaa7fe89acbe7a359",
        "type": "ACTION_SEQUENCE",
        "params": [{
            "datatype": "collection",
            "name": "eventobject"
        }],
        "contextObj": {
            "name": "StoreLocatorScreen",
            "type": "forms",
            "platform": null,
            "KUID": "fa2e1a37cc184fe58a8d471ee6894ecd"
        },
        "sourceObj": {
            "itemKUID": "d166c3ac4a13430d8e2f2dad51099e00",
            "widgetKUID": "e2f6d84750a24a0b99239aefefd70f78",
            "evt": "onClick",
            "platform": null
        },
        "language": "js",
        "actions": [{
            "id": "NAMED_ACTION____9e862374874b409f87047ae8f7e4e8a0",
            "type": "NAMED_ACTION",
            "sequenceKUID": "AS_FlexContainer_c62824988a0e4596ae4e16d5b2fd6578",
            "display": "AS_FlexContainer_c62824988a0e4596ae4e16d5b2fd6578",
            "inputparams": [{
                "datatype": "collection",
                "name": "eventobject",
                "value": "eventobject"
            }],
            "parentId": null,
            "callbackType": null,
            "disabled": false,
            "isMasterInstanceAction": true
        }]
    }
}